PY_Trade_package/Helper.py
PY_Trade_package/MarketDataMart.py
PY_Trade_package/Product.py
PY_Trade_package/SolLog.py
PY_Trade_package/SolPYAPIOB.py
PY_Trade_package/SolPYAPI_Model.py
PY_Trade_package/Sol_HH.py
MasterLinkQuoteH-0.1.7.dist-info/METADATA
MasterLinkQuoteH-0.1.7.dist-info/WHEEL
MasterLinkQuoteH-0.1.7.dist-info/top_level.txt
MasterLinkQuoteH-0.1.7.dist-info/RECORD
